wuddz_pwd_generator/__init__.py
wuddz_pwd_generator/wuddz_pwd.py
wuddz_pwd_generator-1.0.0.dist-info/METADATA
wuddz_pwd_generator-1.0.0.dist-info/WHEEL
wuddz_pwd_generator-1.0.0.dist-info/entry_points.txt
wuddz_pwd_generator-1.0.0.dist-info/licenses/LICENSE
wuddz_pwd_generator-1.0.0.dist-info/RECORD
