Metadata-Version: 2.1
Name: wuddz-pwd-generator
Version: 1.0.0
Summary: Simple Script To Generate A Strong Random Password Of Specified Length & Characters
Project-URL: Homepage, https://github.com/wuddz-devs/Wuddz-Password-Generator
Author-email: Wuddz-Devs <wuddz_devs@protonmail.com>
License: MIT License
License-File: LICENSE
Keywords: generator,password
Classifier: License :: OSI Approved :: MIT License
Classifier: Programming Language :: Python
Classifier: Programming Language :: Python :: 3.6
Classifier: Programming Language :: Python :: 3.7
Classifier: Programming Language :: Python :: 3.8
Classifier: Programming Language :: Python :: 3.9
Classifier: Programming Language :: Python :: 3.10
Requires-Python: >=3.7
